ktu_mon/__init__.py
ktu_mon/__main__.py
ktu_mon/gui/__init__.py
ktu_mon/gui/static/css/bootstrap.min.css
ktu_mon/gui/static/css/bootstrap.min.css.map
ktu_mon/gui/static/icons/ktu-mon-128x128.ico
ktu_mon/gui/static/icons/ktu-mon-32x32.ico
ktu_mon/gui/static/icons/ktu-mon-64x64.ico
ktu_mon/gui/static/icons/ktu-mon.png
ktu_mon/gui/static/icons/bootstrap-icons/bell-fill.svg
ktu_mon/gui/static/icons/bootstrap-icons/graph-up-arrow.svg
ktu_mon/gui/static/icons/bootstrap-icons/house-door-fill.svg
ktu_mon/gui/static/icons/bootstrap-icons/list-check.svg
ktu_mon/gui/static/icons/bootstrap-icons/trash3.svg
ktu_mon/gui/static/icons/bootstrap-icons/fonts/bootstrap-icons.woff
ktu_mon/gui/static/icons/bootstrap-icons/fonts/bootstrap-icons.woff2
ktu_mon/gui/static/js/bootstrap.bundle.min.js
ktu_mon/gui/static/js/bootstrap.bundle.min.js.map
ktu_mon/gui/static/js/chart.umd.js
ktu_mon/gui/static/js/chart.umd.js.map
ktu_mon/gui/templates/added_notifications.html
ktu_mon/gui/templates/base.html
ktu_mon/gui/templates/home.html
ktu_mon/gui/templates/insights.html
ktu_mon/gui/templates/logs.html
ktu_mon/gui/templates/notifications.html
ktu_mon/gui/templates/removed_notifications.html
ktu_mon/systray/__init__.py
ktu_mon/utils/__init__.py
ktu_mon/utils/constants.py
ktu_mon/utils/dbops.py
ktu_mon/utils/scraper.py
ktumon-1.0.1.dist-info/LICENSE
ktumon-1.0.1.dist-info/METADATA
ktumon-1.0.1.dist-info/WHEEL
ktumon-1.0.1.dist-info/entry_points.txt
ktumon-1.0.1.dist-info/top_level.txt
ktumon-1.0.1.dist-info/RECORD
