Metadata-Version: 2.1
Name: ktumon
Version: 1.0.1
Summary: App to monitor notifications published by KTU
Author-email: Anantha Narayanan N <ananthanryn@gmail.com>
License: The MIT License (MIT)
Project-URL: Source, https://github.com/ananthanryn/ktu-mon
Keywords: ktu,ktumon,kerala
Classifier: License :: OSI Approved :: MIT License
Classifier: Development Status :: 5 - Production/Stable
Classifier: Operating System :: Microsoft :: Windows
Classifier: Intended Audience :: Education
Classifier: Intended Audience :: End Users/Desktop
Requires-Python: >=3.11
License-File: LICENSE
Requires-Dist: requests (>=2.28.1)
Requires-Dist: beautifulsoup4 (>=4.11.1)
Requires-Dist: fastapi (>=0.87.0)
Requires-Dist: Jinja2 (>=3.1.2)
Requires-Dist: pystray (>=0.19.4)
Requires-Dist: uvicorn[standard] (>=0.20.0)
Requires-Dist: python-multipart (>=0.0.5)
Provides-Extra: dev
Requires-Dist: black (>=22.12.0) ; extra == 'dev'
Requires-Dist: flake8 (>=6.0.0) ; extra == 'dev'
Requires-Dist: mypy (>=0.991) ; extra == 'dev'
Requires-Dist: build (>=0.9.0) ; extra == 'dev'
Requires-Dist: twine (>=4.0.2) ; extra == 'dev'
